<?xml version="1.0" encoding="UTF-8"?>
<!DOCTYPE mapper PUBLIC "-//mybatis.org//DTD Mapper 3.0//EN" "http://mybatis.org/dtd/mybatis-3-mapper.dtd">
<mapper namespace="com.app.bideo.mapper.member.MemberMapper">
    <insert id="insert" parameterType="com.app.bideo.domain.member.MemberVO" useGeneratedKeys="true" keyProperty="id">
        insert into tbl_member (
            email, password, nickname, real_name, birth_date, phone_number, profile_image, banner_image,
            role, status, creator_verified, seller_verified, creator_tier, follower_count, following_count, gallery_count
        ) values (
            #{email}, #{password}, #{nickname}, #{realName}, #{birthDate}, #{phoneNumber}, #{profileImage}, #{bannerImage},
            #{role}, #{status}, #{creatorVerified}, #{sellerVerified}, #{creatorTier}, #{followerCount}, #{followingCount}, #{galleryCount}
        )
    </insert>

    <select id="selectById" parameterType="long" resultType="com.app.bideo.domain.member.MemberVO">
        select
            id, email, password, nickname, real_name, birth_date, bio, profile_image, banner_image,
            role, creator_verified, seller_verified, creator_tier, follower_count, following_count,
            gallery_count, phone_number, last_login_datetime, status, created_datetime, updated_datetime, deleted_datetime
        from tbl_member
        where id = #{id}
    </select>

    <select id="selectByEmail" parameterType="string" resultType="com.app.bideo.domain.member.MemberVO">
        select
            id, email, password, nickname, real_name, birth_date, bio, profile_image, banner_image,
            role, creator_verified, seller_verified, creator_tier, follower_count, following_count,
            gallery_count, phone_number, last_login_datetime, status, created_datetime, updated_datetime, deleted_datetime
        from tbl_member
        where email = #{email}
          and status = 'ACTIVE'
    </select>

    <select id="selectByNickname" parameterType="string" resultType="com.app.bideo.domain.member.MemberVO"> <!-- 이승민| 프로필 닉네임 경로 조회로 인한 추가 -->
        select
            id, email, password, nickname, real_name, birth_date, bio, profile_image, banner_image,
            role, creator_verified, seller_verified, creator_tier, follower_count, following_count,
            gallery_count, phone_number, last_login_datetime, status, created_datetime, updated_datetime, deleted_datetime
        from tbl_member
        where nickname = #{nickname}
          and status = 'ACTIVE'
    </select>

    <select id="selectByPhoneNumber" parameterType="string" resultType="com.app.bideo.domain.member.MemberVO">
        select
            id, email, password, nickname, real_name, birth_date, bio, profile_image, banner_image,
            role, creator_verified, seller_verified, creator_tier, follower_count, following_count,
            gallery_count, phone_number, last_login_datetime, status, created_datetime, updated_datetime, deleted_datetime
        from tbl_member
        where regexp_replace(coalesce(phone_number, ''), '[^0-9]', '', 'g') = regexp_replace(#{phoneNumber}, '[^0-9]', '', 'g')
          and status = 'ACTIVE'
    </select>

    <select id="existsByEmail" parameterType="string" resultType="boolean">
        select exists(
            select 1
            from tbl_member
            where email = #{email}
        )
    </select>

    <select id="existsByNickname" parameterType="string" resultType="boolean">
        select exists(
            select 1
            from tbl_member
            where nickname = #{nickname}
        )
    </select>

    <update id="updateLastLogin" parameterType="long">
        update tbl_member
        set last_login_datetime = now(),
            updated_datetime = now()
        where id = #{memberId}
    </update>

    <update id="updatePassword">
        update tbl_member
        set password = #{password},
            updated_datetime = now()
        where id = #{memberId}
    </update>

    <update id="updateProfile">
        update tbl_member
        set nickname = #{nickname},
            real_name = #{realName},
            bio = #{bio},
            profile_image = #{profileImage},
            banner_image = #{bannerImage},
            phone_number = #{phoneNumber},
            updated_datetime = now()
        where id = #{memberId}
    </update>

    <select id="countActiveWorksByMemberId" resultType="int">
        select count(*)
        from tbl_work
        where member_id = #{memberId}
          and deleted_datetime is null
          and status != 'DELETED'
    </select>

    <select id="findOwnedBadgesByMemberId" resultType="com.app.bideo.dto.member.MemberBadgeResponseDTO">
        select
            mb.id,
            mb.badge_id,
            b.badge_key,
            b.badge_name,
            b.image_file,
            mb.is_displayed,
            mb.earned_at
        from tbl_member_badge mb
        join tbl_badge b on mb.badge_id = b.id
        where mb.member_id = #{memberId}
        order by mb.is_displayed desc, mb.earned_at desc
    </select>

    <select id="findDisplayedBadgesByMemberId" resultType="com.app.bideo.dto.member.MemberBadgeResponseDTO">
        select
            mb.id,
            mb.badge_id,
            b.badge_key,
            b.badge_name,
            b.image_file,
            mb.is_displayed,
            mb.earned_at
        from tbl_member_badge mb
        join tbl_badge b on mb.badge_id = b.id
        where mb.member_id = #{memberId}
          and mb.is_displayed = true
        order by mb.earned_at desc
    </select>

    <update id="clearDisplayedBadges">
        update tbl_member_badge
        set is_displayed = false
        where member_id = #{memberId}
    </update>

    <update id="displayBadges">
        update tbl_member_badge
        set is_displayed = true
        where member_id = #{memberId}
          and badge_id in
        <foreach collection="badgeIds" item="badgeId" open="(" separator="," close=")">
            #{badgeId}
        </foreach>
    </update>

    <select id="searchByKeyword" resultType="com.app.bideo.dto.member.MemberListResponseDTO">
        SELECT
            m.id,
            m.nickname,
            m.profile_image,
            m.bio,
            m.creator_verified,
            m.creator_tier,
            m.follower_count
        FROM tbl_member m
        WHERE m.status = 'ACTIVE'
          AND m.id != #{currentMemberId}
          AND (
              m.nickname ILIKE '%' || #{keyword} || '%'
              OR m.real_name ILIKE '%' || #{keyword} || '%'
              OR m.bio ILIKE '%' || #{keyword} || '%'
          )
        ORDER BY m.follower_count DESC NULLS LAST
        LIMIT #{limit}
    </select>

    <select id="searchByKeywordPaged" resultType="com.app.bideo.dto.member.MemberListResponseDTO">
        SELECT
            m.id,
            m.nickname,
            m.profile_image,
            m.bio,
            m.creator_verified,
            m.creator_tier,
            m.follower_count,
            CASE WHEN f.id IS NOT NULL THEN true ELSE false END AS is_following
        FROM tbl_member m
        LEFT JOIN tbl_follow f ON f.follower_id = #{currentMemberId}
                              AND f.following_id = m.id
        WHERE m.status = 'ACTIVE'
          AND m.id != #{currentMemberId}
          AND (
              m.nickname ILIKE '%' || #{keyword} || '%'
              OR m.real_name ILIKE '%' || #{keyword} || '%'
              OR m.bio ILIKE '%' || #{keyword} || '%'
          )
        ORDER BY m.follower_count DESC NULLS LAST
        LIMIT #{criteria.count} OFFSET #{criteria.offset}
    </select>

</mapper>
